{
"type": "FeatureCollection",
"_circuit": "britain_v1",
"_layer": "sectors",
"_label": "Silverstone",
"_note": "S1=end of sector 1. S2=end of sector 2. T=speed trap. S3 ends at start\/finish — no point needed.",
"name": "sectors",
"features": [
{ "type": "Feature", "id": "S1", "properties": { "sector": "S1", "ref": "110m before T6", "circuit": "britain_v1", "notes": "" }, "geometry": null },
{ "type": "Feature", "id": "S2", "properties": { "sector": "S2", "ref": "see PDF", "circuit": "britain_v1", "notes": "" }, "geometry": null },
{ "type": "Feature", "id": "T", "properties": { "sector": "T", "ref": "see PDF", "circuit": "britain_v1", "notes": "" }, "geometry": null },
{ "type": "Feature", "properties": { "id": null, "sector": "SPEED TRAP", "ref": null, "circuit": "SILVERSTONE", "notes": null }, "geometry": { "type": "Point", "coordinates": [ -1.016378168484043, 52.064061509574472 ] } },
{ "type": "Feature", "properties": { "id": "1", "sector": "SECTOR 1", "ref": null, "circuit": "SILVERSTONE", "notes": null }, "geometry": { "type": "Point", "coordinates": [ -1.017997530984043, 52.076740773404261 ] } },
{ "type": "Feature", "properties": { "id": "2", "sector": "SECTOR 2", "ref": null, "circuit": "SILVERSTONE", "notes": null }, "geometry": { "type": "Point", "coordinates": [ -1.011761262632979, 52.069212460505319 ] } }
]
}
