{
"type": "FeatureCollection",
"_layer": "start_finish",
"_note": "Single Point. Place exactly on the painted start\/finish line on the track centreline in QGIS. Not the pit exit, not the grid boxes — the actual line on the tarmac.",
"name": "start_finish_v2",
"features": [
{ "type": "Feature", "id": "start_finish_line", "properties": { "type": "start_finish_line", "circuit_folder": "abu_dhabi", "notes": "Place on painted start/finish line, centreline" }, "geometry": null },
{ "type": "Feature", "properties": { "id": null, "type": null, "circuit_folder": null, "notes": null }, "geometry": { "type": "Point", "coordinates": [ 54.604265300251257, 24.469772135263675 ] } },
{ "type": "Feature", "properties": { "id": "1", "type": "START/FINSIH PT", "circuit_folder": "ABU DHABHI", "notes": null }, "geometry": { "type": "Point", "coordinates": [ 54.604149147332983, 24.469791494083385 ] } }
]
}
