{
"type": "FeatureCollection",
"_layer": "start_finish",
"_note": "Single Point. Place exactly on the painted start\/finish line on the track centreline in QGIS. Not the pit exit, not the grid boxes — the actual line on the tarmac.",
"name": "start_finish",
"features": [
{ "type": "Feature", "id": "start_finish_line", "properties": { "type": "start_finish_line", "circuit_folder": "cota", "notes": "Place on painted start/finish line, centreline" }, "geometry": null },
{ "type": "Feature", "properties": { "id": null, "type": "START/FINSIH PT", "circuit_folder": "COTA", "notes": null }, "geometry": { "type": "Point", "coordinates": [ -97.642251172510285, 30.133532817376118 ] } }
]
}
