{
"type": "FeatureCollection",
"_circuit": "dutch_v1",
"_layer": "sectors",
"_label": "Circuit Zandvoort",
"_note": "S1=end of sector 1. S2=end of sector 2. T=speed trap. S3 ends at start\/finish — no point needed.",
"name": "sectors",
"features": [
{ "type": "Feature", "id": "S1", "properties": { "sector": "S1", "ref": "95m before T1", "circuit": "dutch_v1", "notes": "" }, "geometry": null },
{ "type": "Feature", "id": "S2", "properties": { "sector": "S2", "ref": "150m before T11", "circuit": "dutch_v1", "notes": "" }, "geometry": null },
{ "type": "Feature", "id": "T", "properties": { "sector": "T", "ref": "110m before T7", "circuit": "dutch_v1", "notes": "" }, "geometry": null },
{ "type": "Feature", "properties": { "id": null, "sector": "SPEED TRAP", "ref": null, "circuit": "ZANDVOORT", "notes": null }, "geometry": { "type": "Point", "coordinates": [ 4.54243267438247, 52.391270183007968 ] } },
{ "type": "Feature", "properties": { "id": " 1", "sector": "SECTOR 1", "ref": null, "circuit": "ZANDVOORT", "notes": null }, "geometry": { "type": "Point", "coordinates": [ 4.549837375199203, 52.38896183498008 ] } },
{ "type": "Feature", "properties": { "id": "2", "sector": "SECTOR 2", "ref": null, "circuit": "ZANDVOORT", "notes": null }, "geometry": { "type": "Point", "coordinates": [ 4.545370571872509, 52.387672757509961 ] } }
]
}
