{
"type": "FeatureCollection",
"_circuit": "bahrain_sakhir_v1",
"_layer": "sectors",
"_label": "Bahrain Outer — Sakhir 2020",
"_note": "S1=end of sector 1. S2=end of sector 2. T=speed trap. S3 ends at start\/finish — no point needed.",
"name": "sectors",
"features": [
{ "type": "Feature", "id": "S1", "properties": { "sector": "S1", "ref": "290m before T4", "circuit": "bahrain_sakhir_v1", "notes": "" }, "geometry": null },
{ "type": "Feature", "id": "S2", "properties": { "sector": "S2", "ref": "10m after T9", "circuit": "bahrain_sakhir_v1", "notes": "" }, "geometry": null },
{ "type": "Feature", "id": "T", "properties": { "sector": "T", "ref": "158m before T1", "circuit": "bahrain_sakhir_v1", "notes": "" }, "geometry": null },
{ "type": "Feature", "properties": { "id": null, "sector": "SPEED TRAP", "ref": null, "circuit": "SAKHIR", "notes": null }, "geometry": { "type": "Point", "coordinates": [ 50.510651191329792, 26.036219562031913 ] } },
{ "type": "Feature", "properties": { "id": "1", "sector": "SECTOR 1", "ref": null, "circuit": "SAKHIR", "notes": null }, "geometry": { "type": "Point", "coordinates": [ 50.516417075542556, 26.035977297989358 ] } },
{ "type": "Feature", "properties": { "id": "2", "sector": "SECTOR 2", "ref": null, "circuit": "SAKHIR", "notes": null }, "geometry": { "type": "Point", "coordinates": [ 50.516477641553195, 26.028878961542549 ] } }
]
}
